groster/__init__.py
groster/__main__.py
groster/cli.py
groster/constants.py
groster/http_client.py
groster/models.py
groster/ranks.py
groster/services.py
groster/utils.py
groster-0.4.0.dist-info/METADATA
groster-0.4.0.dist-info/WHEEL
groster-0.4.0.dist-info/entry_points.txt
groster-0.4.0.dist-info/licenses/LICENSE
groster-0.4.0.dist-info/RECORD
