Metadata-Version: 2.4
Name: groster
Version: 0.4.0
Summary: A tool to fetch and process World of Warcraft guild rosters, identifying player information via the Blizzard API.
Project-URL: Homepage, https://github.com/sergeyklay/groster
Project-URL: Repository, https://github.com/sergeyklay/groster
Project-URL: Issues, https://github.com/sergeyklay/groster/issues
Project-URL: Download, https://github.com/sergeyklay/groster/releases
Author-email: Serghei Iakovlev <oss@serghei.pl>
Maintainer-email: Serghei Iakovlev <oss@serghei.pl>
License: The MIT License (MIT)
License-File: LICENSE
Keywords: game,mmorpg,world-of-warcraft,wow
Classifier: Development Status :: 4 - Beta
Classifier: Environment :: Console
Classifier: Intended Audience :: Developers
Classifier: License :: OSI Approved :: MIT License
Classifier: Operating System :: OS Independent
Classifier: Programming Language :: Python :: 3
Classifier: Programming Language :: Python :: 3.12
Classifier: Programming Language :: Python :: 3.13
Classifier: Programming Language :: Python :: 3.14
Classifier: Programming Language :: Python :: 3.15
Classifier: Programming Language :: Python :: Implementation :: CPython
Classifier: Topic :: Games/Entertainment :: Role-Playing
Classifier: Topic :: Utilities
Classifier: Typing :: Typed
Requires-Python: <4,>=3.12
Requires-Dist: httpx>=0.28.1
Requires-Dist: pandas>=2.3.3
Requires-Dist: python-dotenv>=1.1.1
